huntflow_py/api.py
huntflow_py/client.py
huntflow_py-0.1.1.dist-info/WHEEL
huntflow_py-0.1.1.dist-info/METADATA
huntflow_py-0.1.1.dist-info/RECORD
