Metadata-Version: 2.1
Name: huntflow-py
Version: 0.1.1
Summary: Huntflow API library for Python
Home-page: https://github.com/agrrh/huntflow-py
License: WTFPL
Author: Kirill K
Author-email: kovalev.kirill.a@gmail.com
Requires-Python: >=3.6,<4.0
Classifier: License :: Other/Proprietary License
Classifier: Programming Language :: Python :: 3
Classifier: Programming Language :: Python :: 3.6
Classifier: Programming Language :: Python :: 3.7
Classifier: Programming Language :: Python :: 3.8
Requires-Dist: email_validator (>=1.1.0,<2.0.0)
Requires-Dist: requests (>=2.23.0,<3.0.0)
Project-URL: Repository, https://github.com/agrrh/huntflow-py
